pmcc/__init__.py
pmcc/__main__.py
pmcc/adapters.py
pmcc/alerts.py
pmcc/approval.py
pmcc/cache.py
pmcc/connectors.py
pmcc/contracts.py
pmcc/data.py
pmcc/execution.py
pmcc/ext.py
pmcc/filters.py
pmcc/health.py
pmcc/ibkr_mock.py
pmcc/integration.py
pmcc/jsonlog.py
pmcc/main.py
pmcc/metrics.py
pmcc/monitor.py
pmcc/options_synth.py
pmcc/portfolio.py
pmcc/pretrade.py
pmcc/providers.py
pmcc/real_http_provider.py
pmcc/real_readonly.py
pmcc/real_spec.py
pmcc/retry.py
pmcc/risk.py
pmcc/strategy.py
pmcc/ta.py
pmcc/throttle.py
pmcc/utils.py
pmcc_quantitative_strategy-1.0.4.dist-info/METADATA
pmcc_quantitative_strategy-1.0.4.dist-info/WHEEL
pmcc_quantitative_strategy-1.0.4.dist-info/entry_points.txt
pmcc_quantitative_strategy-1.0.4.dist-info/top_level.txt
pmcc_quantitative_strategy-1.0.4.dist-info/RECORD
