Metadata-Version: 2.4
Name: pmcc-quantitative-strategy
Version: 1.0.4
Summary: PMCC quantitative strategy prototype (dry-run)
Author: PMCC Team
Requires-Python: >=3.10
